{
  "poCreate": {
    "status": 201,
    "data": {
      "id": 3,
      "poNumber": "PO-00003",
      "vendorId": 3,
      "vendorName": "Steel Supply Co",
      "jobId": null,
      "jobNumber": null,
      "status": "Draft",
      "lineCount": 1,
      "totalOrdered": 10,
      "totalReceived": 0,
      "expectedDeliveryDate": null,
      "isBlanket": false,
      "createdAt": "2026-05-22T07:14:35.7326535+00:00",
      "belowVendorMinimum": false
    }
  },
  "poSubmit": {
    "status": 204,
    "data": ""
  },
  "poAck": {
    "status": 204,
    "data": ""
  },
  "poDetail": {
    "id": 3,
    "poNumber": "PO-00003",
    "vendorId": 3,
    "vendorName": "Steel Supply Co",
    "jobId": null,
    "jobNumber": null,
    "status": "Acknowledged",
    "submittedDate": "2026-05-22T09:53:40.169079+00:00",
    "acknowledgedDate": "2026-05-22T09:53:40.185332+00:00",
    "expectedDeliveryDate": "2026-05-29T00:00:00+00:00",
    "receivedDate": null,
    "notes": "Q6-h receiving test",
    "isBlanket": false,
    "blanketTotalQuantity": null,
    "blanketReleasedQuantity": null,
    "blanketRemainingQuantity": null,
    "blanketExpirationDate": null,
    "agreedUnitPrice": null,
    "lines": [
      {
        "id": 3,
        "partId": 4,
        "partNumber": "PRT-00003",
        "description": "Test Part C6G",
        "orderedQuantity": 10,
        "receivedQuantity": 0,
        "remainingQuantity": 10,
        "cancelledShortCloseQuantity": 0,
        "unitPrice": 25,
        "lineTotal": 250,
        "notes": null
      }
    ],
    "createdAt": "2026-05-22T07:14:35.732653+00:00",
    "updatedAt": "2026-05-22T07:14:35.732653+00:00",
    "shortCloseReason": null,
    "shortClosedAt": null,
    "incoterm": "FOB_Origin",
    "estimatedFreight": null,
    "quoteCurrency": "USD",
    "fxRate": 1,
    "fxRateSource": "auto: same-currency (USD)",
    "belowVendorMinimum": false,
    "vendorMinimumOrderAmount": null
  },
  "poReceive": {
    "status": 204,
    "data": ""
  },
  "receivingState": {
    "hasReceivingComp": false,
    "compText": "",
    "invText": "INVENTORY\nTrack stock levels, locations, and movements\nhelp_outline\nadd\nRECEIVE GOODS\ninventory\nSTOCK LEVELS\nwarehouse\nLOCATIONS\nswap_horiz\nMOVEMENTS\nlocal_shipping\nRECEIVING\ntune\nSTOCK OPS\nfact_check\nCYCLE COUNTS\nlock\nRESERVATIONS\nshopping_cart\nREPLENISHMENT\nstraighten\nUNITS OF MEASURE\n2 RECORDS\nPO #\nmore_vert\n\t\nPART #\nmore_vert\n\t\nQTY\nmore_vert\n\t\nRECEIVED BY\nmore_vert\n\t\nLOCATION\nmore_vert\n\t\nLOT #\nmore_vert\n\t\nDATE\nmore_vert\n\t\ndownload\ngrid_on\nsettings\n\nPO-00002\tPRT-00003\t10\t\tBIN-A1-01\t—\t05/22/2026 01:14 AM\t\nPO-00003\tPRT-00003\t10\t\tBIN-A1-01\t—\t05/22/2026 01:14 AM\t",
    "hasEmptyState": false,
    "allApp": [
      "app-root",
      "app-header",
      "app-chat",
      "app-ai-help-panel",
      "app-training-context-panel",
      "app-connection-banner",
      "app-announcement-overlay",
      "app-onboarding-banner",
      "app-sidebar",
      "app-inventory",
      "app-page-header",
      "app-data-table",
      "app-offline-banner",
      "app-loading-overlay",
      "app-toast-container",
      "app-keyboard-shortcuts-help",
      "app-chat-preview-popup",
      "app-demo-marker"
    ]
  },
  "poListState": {
    "allApp": [
      "app-root",
      "app-header",
      "app-chat",
      "app-ai-help-panel",
      "app-training-context-panel",
      "app-connection-banner",
      "app-announcement-overlay",
      "app-onboarding-banner",
      "app-sidebar",
      "app-purchase-orders",
      "app-page-header",
      "app-input",
      "app-select",
      "app-data-table",
      "app-offline-banner",
      "app-loading-overlay",
      "app-toast-container",
      "app-keyboard-shortcuts-help",
      "app-chat-preview-popup",
      "app-demo-marker"
    ],
    "bodyText": "Skip to main content\nHOME\nchevron_right\nPURCHASING\nchevron_right\nPURCHASE ORDERS\nsearch\nCtrl+K\nschool\nnotifications_none\nlight_mode\nAdmin, Forge\nmenu\narrow_back\nstorefront\ndescription\nrequest_page\nstorefront\nsettings\nPURCHASE ORDERS\nOrder materials and track vendor deliveries\nadd\nNEW PO\ndescription\nORDERS\nauto_awesome\nSUGGESTIONS\nsettings\nSETTINGS\nSearch\nVendor\nStatus\nPO #\nmore_vert\n\t\nVENDOR\nmore_vert\n\t\nJOB\nmore_vert\n\t\nSTATUS\nmore_vert\n\t\nLINES\nmore_vert\n\t\nORDERED\nmore_vert\n\t\nRECEIVED\nmore_vert\n\t\nEXPECTED\nmore_vert\n\t\nCREATED\nmore_vert\n\t\ndownload\ngrid_on\nsettings\n\nPO-00001\tSteel Supply Co\t—\t\nACKNOWLEDGED\n\t1\t10\t0\t05/28/2026\t05/22/2026\t\nPO-00002\tSteel Supply Co\t—\t\nRECEIVED\n\t1\t10\t10\t05/28/2026\t05/22/2026\t\nPO-00003\tSteel Supply Co\t—\t\nRECEIVED\n\t1\t10\t10\t05/28/2026\t05/22/2026\t"
  }
}